tonbo-0.1.0.dist-info/METADATA
tonbo-0.1.0.dist-info/WHEEL
tonbo/error.pyi
tonbo/__init__.pyi
tonbo/__init__.py
tonbo/fs.pyi
tonbo/_tonbo.abi3.so
tonbo-0.1.0.dist-info/RECORD
