Metadata-Version: 2.3
Name: tonbo
Version: 0.1.0
Classifier: Programming Language :: Rust
Classifier: Programming Language :: Python :: Implementation :: CPython
Classifier: Programming Language :: Python :: Implementation :: PyPy
Requires-Dist: pytest ; extra == 'test'
Requires-Dist: pytest-asyncio ; extra == 'test'
Requires-Dist: pytest ; extra == 'bench'
Requires-Dist: pytest-asyncio ; extra == 'bench'
Requires-Dist: pytest-benchmark ; extra == 'bench'
Requires-Dist: duckdb ; extra == 'bench'
Requires-Dist: pdoc ; extra == 'docs'
Provides-Extra: test
Provides-Extra: bench
Provides-Extra: docs
Summary: Tonbo Python Binding
License: Apache-2.0
Requires-Python: >=3.10
Project-URL: Source Code, https://github.com/tonbo-io/tonbo
